gradePhyX/__init__.py
gradePhyX/scoring.py
gradePhyX/utils/__init__.py
gradePhyX/utils/data_loading_utils.py
gradePhyX/utils/data_utils.py
gradePhyX/utils/default_hyperparams.py
gradePhyX/utils/multi_students_multi_problems_scoring_utils.py
gradePhyX/utils/simplify_expression.py
gradePhyX/utils/singleProblemFormulasTypes.py
gradePhyX/utils/singleStudentAnswerTypes.py
gradePhyX/utils/single_formula_comparison_utils.py
gradephyx-1.0.2.dist-info/licenses/LICENSE
gradephyx-1.0.2.dist-info/licenses/LICENSE.txt
gradephyx-1.0.2.dist-info/METADATA
gradephyx-1.0.2.dist-info/WHEEL
gradephyx-1.0.2.dist-info/top_level.txt
gradephyx-1.0.2.dist-info/RECORD
